receiptrecognizer/__init__.py
receiptrecognizer/module.py
receiptrecognizer/analyzer/__init__.py
receiptrecognizer/analyzer/filter.py
receiptrecognizer/analyzer/metrics.py
receiptrecognizer/datasets/__init__.py
receiptrecognizer/datasets/recognitiondataset.py
receiptrecognizer/downloaders/__init__.py
receiptrecognizer/downloaders/google_downloader.py
receiptrecognizer/models/__init__.py
receiptrecognizer/models/backbones/__init__.py
receiptrecognizer/models/backbones/rcnn.py
receiptrecognizer/models/backbones/resnet.py
receiptrecognizer/models/backbones/vgg.py
receiptrecognizer/models/craft/__init__.py
receiptrecognizer/models/craft/craft.py
receiptrecognizer/models/craft/blocks/__init__.py
receiptrecognizer/models/craft/blocks/double_conv.py
receiptrecognizer/models/refinenet/__init__.py
receiptrecognizer/models/refinenet/refinenet.py
receiptrecognizer/models/resbilstmattn/__init__.py
receiptrecognizer/models/resbilstmattn/resbilstmattn.py
receiptrecognizer/models/resbilstmattn/blocks/__init__.py
receiptrecognizer/models/resbilstmattn/blocks/attention.py
receiptrecognizer/models/resbilstmattn/blocks/bilstm.py
receiptrecognizer/models/tesseract/__init__.py
receiptrecognizer/models/tesseract/tesseract.py
receiptrecognizer/models/utils/__init__.py
receiptrecognizer/models/utils/spatial_transformation.py
receiptrecognizer/models/utils/weights.py
receiptrecognizer/transforms/__init__.py
receiptrecognizer/transforms/labelconverter.py
receiptrecognizer/transforms/postprocess.py
receiptrecognizer/transforms/preprocess.py
receiptrecognizer/utils/__init__.py
receiptrecognizer/utils/file_utils.py
receiptrecognizer/utils/image_utils.py
receiptrecognizer/utils/model_utils.py
receiptrecognizer-0.0.5.1.dist-info/LICENSE
receiptrecognizer-0.0.5.1.dist-info/METADATA
receiptrecognizer-0.0.5.1.dist-info/WHEEL
receiptrecognizer-0.0.5.1.dist-info/top_level.txt
receiptrecognizer-0.0.5.1.dist-info/RECORD
