Metadata-Version: 2.1
Name: receiptrecognizer
Version: 0.0.5.1
Summary: Receipt Recognition Package
Home-page: https://github.com/kemalaraz/Receipt_Recognizer
Author: karaz
Author-email: kemalaraz91@gmail.com
License: UNKNOWN
Platform: UNKNOWN
Classifier: Programming Language :: Python :: 3
Classifier: License :: OSI Approved :: MIT License
Classifier: Operating System :: OS Independent
Requires-Python: <3.8
Requires-Dist: numpy
Requires-Dist: natsort
Requires-Dist: imutils
Requires-Dist: shapely
Requires-Dist: requests
Requires-Dist: pytesseract
Requires-Dist: scikit-image
Requires-Dist: torch (==1.5.1)
Requires-Dist: torchvision
Requires-Dist: opencv-python
Requires-Dist: googledrivedownloader (==0.4)
